tests_common/__init__.py
tests_common/pytest_plugin.py
tests_common/_internals/__init__.py
tests_common/_internals/capture_warnings.py
tests_common/_internals/forbidden_warnings.py
tests_common/test_utils/README.md
tests_common/test_utils/__init__.py
tests_common/test_utils/api_client_helpers.py
tests_common/test_utils/api_fastapi.py
tests_common/test_utils/asserts.py
tests_common/test_utils/azure_system_helpers.py
tests_common/test_utils/common_sql.py
tests_common/test_utils/compat.py
tests_common/test_utils/config.py
tests_common/test_utils/db.py
tests_common/test_utils/executor_loader.py
tests_common/test_utils/fake_datetime.py
tests_common/test_utils/file_loading.py
tests_common/test_utils/format_datetime.py
tests_common/test_utils/gcp_system_helpers.py
tests_common/test_utils/get_all_tests.py
tests_common/test_utils/hdfs_utils.py
tests_common/test_utils/log_handlers.py
tests_common/test_utils/logging_command_executor.py
tests_common/test_utils/logs.py
tests_common/test_utils/mapping.py
tests_common/test_utils/markers.py
tests_common/test_utils/mock_context.py
tests_common/test_utils/mock_executor.py
tests_common/test_utils/mock_operators.py
tests_common/test_utils/mock_plugins.py
tests_common/test_utils/mock_security_manager.py
tests_common/test_utils/otel_utils.py
tests_common/test_utils/paths.py
tests_common/test_utils/permissions.py
tests_common/test_utils/providers.py
tests_common/test_utils/reset_warning_registry.py
tests_common/test_utils/salesforce_system_helpers.py
tests_common/test_utils/sftp_system_helpers.py
tests_common/test_utils/system_tests.py
tests_common/test_utils/system_tests_class.py
tests_common/test_utils/terraform.py
tests_common/test_utils/timetables.py
tests_common/test_utils/version_compat.py
tests_common/test_utils/watcher.py
tests_common/test_utils/operators/__init__.py
tests_common/test_utils/operators/postgres_local_executor.cfg
tests_common/test_utils/operators/run_deferrable.py
tests_common/test_utils/perf/__init__.py
apache_airflow_devel_common-0.1.1.dist-info/entry_points.txt
apache_airflow_devel_common-0.1.1.dist-info/WHEEL
apache_airflow_devel_common-0.1.1.dist-info/METADATA
apache_airflow_devel_common-0.1.1.dist-info/RECORD
